mva/__init__.py
mva/mva.py
mva-0.0.2.dist-info/LICENSE
mva-0.0.2.dist-info/METADATA
mva-0.0.2.dist-info/WHEEL
mva-0.0.2.dist-info/top_level.txt
mva-0.0.2.dist-info/RECORD
