Metadata-Version: 2.1
Name: mva
Version: 0.0.2
Summary: A package to correct the bias of forecasts/hindcasts. Read the documentation at https://github.com/gouthamnaveen/mva
Home-page: https://github.com/gouthamnaveen/mva
Author: Naveen Goutham
Author-email: naveen.goutham@outlook.com
License: Apache License 2.0
Keywords: mva,mean,variance,bias correction,mean and variance adjustment,bias adjustment,calibration,python
Platform: UNKNOWN
License-File: LICENSE
Requires-Dist: numpy
